Workbook

Sheet Dashboard
A1: Multi-Branch Financial Dashboard
A2: لوحة موحدة لفروع MBZ وMussafah وAl Falah — القيم تتحدث من الصفحات المرتبطة
A4: As of Date | B4: =TODAY()
A6: Book Bank & Cash | C6: Available Liquidity | E6: Commitments — 30 Days | G6: Commitments — 60 Days | I6: Commitments — 90 Days | K6: Liquidity Coverage
A7: =SUM('Bank & Cash Balances'!$F$5:$F$104) | C7: =SUM('Bank & Cash Balances'!$I$5:$I$104) | E7: =SUMIFS(Commitments!$L$5:$L$504,Commitments!$E$5:$E$504,">="&TODAY(),Commitments!$E$5:$E$504,"<="&TODAY()+30,Commitments!$M$5:$M$504,"<>Paid",Commitments!$M$5:$M$504,"<>Cancelled") | G7: =SUMIFS(Commitments!$L$5:$L$504,Commitments!$E$5:$E$504,">"&TODAY()+30,Commitments!$E$5:$E$504,"<="&TODAY()+60,Commitments!$M$5:$M$504,"<>Paid",Commitments!$M$5:$M$504,"<>Cancelled") | I7: =SUMIFS(Commitments!$L$5:$L$504,Commitments!$E$5:$E$504,">"&TODAY()+60,Commitments!$E$5:$E$504,"<="&TODAY()+90,Commitments!$M$5:$M$504,"<>Paid",Commitments!$M$5:$M$504,"<>Cancelled") | K7: =IFERROR(C7/E7,0)
A10: Cheques Due This Month | C10: Salaries Due | E10: Unpaid Purchases | G10: Overdue Suppliers | I10: Open Commitments | K10: Next Month Closing
A11: =SUMIFS('Cheque Register'!$H$5:$H$304,'Cheque Register'!$G$5:$G$304,">="&EOMONTH(TODAY(),-1)+1,'Cheque Register'!$G$5:$G$304,"<="&EOMONTH(TODAY(),0),'Cheque Register'!$I$5:$I$304,"Pending") | C11: =SUMIFS(Commitments!$L$5:$L$504,Commitments!$F$5:$F$504,"Salaries",Commitments!$M$5:$M$504,"<>Paid",Commitments!$M$5:$M$504,"<>Cancelled") | E11: =SUM('Accounts Payable'!$K$5:$K$504) | G11: =SUMIFS('Accounts Payable'!$K$5:$K$504,'Accounts Payable'!$F$5:$F$504,"<"&TODAY(),'Accounts Payable'!$L$5:$L$504,"<>Paid",'Accounts Payable'!$L$5:$L$504,"<>Cancelled") | I11: =SUMIFS(Commitments!$L$5:$L$504,Commitments!$M$5:$M$504,"<>Paid",Commitments!$M$5:$M$504,"<>Cancelled") | K11: ='Cash Flow Forecast'!H6
A14: 12-Month Obligations | B14: Expected Expenses | C14: Closing Balance
A15: ='Cash Flow Forecast'!A5 | B15: ='Cash Flow Forecast'!F5 | C15: ='Cash Flow Forecast'!H5
A16: ='Cash Flow Forecast'!A6 | B16: ='Cash Flow Forecast'!F6 | C16: ='Cash Flow Forecast'!H6
A17: ='Cash Flow Forecast'!A7 | B17: ='Cash Flow Forecast'!F7 | C17: ='Cash Flow Forecast'!H7
A18: ='Cash Flow Forecast'!A8 | B18: ='Cash Flow Forecast'!F8 | C18: ='Cash Flow Forecast'!H8
A19: ='Cash Flow Forecast'!A9 | B19: ='Cash Flow Forecast'!F9 | C19: ='Cash Flow Forecast'!H9
A20: ='Cash Flow Forecast'!A10 | B20: ='Cash Flow Forecast'!F10 | C20: ='Cash Flow Forecast'!H10
A21: ='Cash Flow Forecast'!A11 | B21: ='Cash Flow Forecast'!F11 | C21: ='Cash Flow Forecast'!H11
A22: ='Cash Flow Forecast'!A12 | B22: ='Cash Flow Forecast'!F12 | C22: ='Cash Flow Forecast'!H12
A23: ='Cash Flow Forecast'!A13 | B23: ='Cash Flow Forecast'!F13 | C23: ='Cash Flow Forecast'!H13
A24: ='Cash Flow Forecast'!A14 | B24: ='Cash Flow Forecast'!F14 | C24: ='Cash Flow Forecast'!H14
A25: ='Cash Flow Forecast'!A15 | B25: ='Cash Flow Forecast'!F15 | C25: ='Cash Flow Forecast'!H15
A26: ='Cash Flow Forecast'!A16 | B26: ='Cash Flow Forecast'!F16 | C26: ='Cash Flow Forecast'!H16
A29: Alert Logic
A30: Red: overdue supplier invoice, cheque due within 7 days, or negative forecast.
A31: Orange: payment due soon or liquidity below protected minimum.
A32: Source Type + Source ID must be unique before importing a commitment.
A33: Fixed templates feed the forecast; generated Fixed commitments are excluded from forecast commitments to prevent double counting.

Sheet Commitments
A1: Future Commitments — Central Register
A2: السجل المركزي الوحيد للالتزامات؛ استخدم Source Type + Source ID لمنع العدّ المزدوج
A4: Commitment ID | B4: Source Type | C4: Source ID | D4: Branch | E4: Due Date | F4: Category | G4: Description | H4: Supplier / Payee | I4: Amount (AED) | J4: Payment Method | K4: Paid Amount (AED) | L4: Balance (AED) | M4: Status | N4: Priority | O4: Recurring | P4: Payment Date | Q4: Bank Account | R4: Approved By | S4: Notes | T4: Days to Due | U4: Alert
L5: =IF(I5="","",MAX(0,I5-K5)) | T5: =IF(E5="","",E5-TODAY()) | U5: =IF(OR(M5="Paid",M5="Cancelled",E5=""),"",IF(E5<TODAY(),"OVERDUE",IF(E5<=TODAY()+'Setup & Lists'!$M$7,"DUE SOON","")))
L6: =IF(I6="","",MAX(0,I6-K6)) | T6: =IF(E6="","",E6-TODAY()) | U6: =IF(OR(M6="Paid",M6="Cancelled",E6=""),"",IF(E6<TODAY(),"OVERDUE",IF(E6<=TODAY()+'Setup & Lists'!$M$7,"DUE SOON","")))
L7: =IF(I7="","",MAX(0,I7-K7)) | T7: =IF(E7="","",E7-TODAY()) | U7: =IF(OR(M7="Paid",M7="Cancelled",E7=""),"",IF(E7<TODAY(),"OVERDUE",IF(E7<=TODAY()+'Setup & Lists'!$M$7,"DUE SOON","")))
L8: =IF(I8="","",MAX(0,I8-K8)) | T8: =IF(E8="","",E8-TODAY()) | U8: =IF(OR(M8="Paid",M8="Cancelled",E8=""),"",IF(E8<TODAY(),"OVERDUE",IF(E8<=TODAY()+'Setup & Lists'!$M$7,"DUE SOON","")))
L9: =IF(I9="","",MAX(0,I9-K9)) | T9: =IF(E9="","",E9-TODAY()) | U9: =IF(OR(M9="Paid",M9="Cancelled",E9=""),"",IF(E9<TODAY(),"OVERDUE",IF(E9<=TODAY()+'Setup & Lists'!$M$7,"DUE SOON","")))
L10: =IF(I10="","",MAX(0,I10-K10)) | T10: =IF(E10="","",E10-TODAY()) | U10: =IF(OR(M10="Paid",M10="Cancelled",E10=""),"",IF(E10<TODAY(),"OVERDUE",IF(E10<=TODAY()+'Setup & Lists'!$M$7,"DUE SOON","")))
L11: =IF(I11="","",MAX(0,I11-K11)) | T11: =IF(E11="","",E11-TODAY()) | U11: =IF(OR(M11="Paid",M11="Cancelled",E11=""),"",IF(E11<TODAY(),"OVERDUE",IF(E11<=TODAY()+'Setup & Lists'!$M$7,"DUE SOON","")))
L12: =IF(I12="","",MAX(0,I12-K12)) | T12: =IF(E12="","",E12-TODAY()) | U12: =IF(OR(M12="Paid",M12="Cancelled",E12=""),"",IF(E12<TODAY(),"OVERDUE",IF(E12<=TODAY()+'Setup & Lists'!$M$7,"DUE SOON","")))
L13: =IF(I13="","",MAX(0,I13-K13)) | T13: =IF(E13="","",E13-TODAY()) | U13: =IF(OR(M13="Paid",M13="Cancelled",E13=""),"",IF(E13<TODAY(),"OVERDUE",IF(E13<=TODAY()+'Setup & Lists'!$M$7,"DUE SOON","")))
L14: =IF(I14="","",MAX(0,I14-K14)) | T14: =IF(E14="","",E14-TODAY()) | U14: =IF(OR(M14="Paid",M14="Cancelled",E14=""),"",IF(E14<TODAY(),"OVERDUE",IF(E14<=TODAY()+'Setup & Lists'!$M$7,"DUE SOON","")))
L15: =IF(I15="","",MAX(0,I15-K15)) | T15: =IF(E15="","",E15-TODAY()) | U15: =IF(OR(M15="Paid",M15="Cancelled",E15=""),"",IF(E15<TODAY(),"OVERDUE",IF(E15<=TODAY()+'Setup & Lists'!$M$7,"DUE SOON","")))
L16: =IF(I16="","",MAX(0,I16-K16)) | T16: =IF(E16="","",E16-TODAY()) | U16: =IF(OR(M16="Paid",M16="Cancelled",E16=""),"",IF(E16<TODAY(),"OVERDUE",IF(E16<=TODAY()+'Setup & Lists'!$M$7,"DUE SOON","")))
... L504: =IF(I504="","",MAX(0,I504-K504)) | T504: =IF(E504="","",E504-TODAY()) | U504: =IF(OR(M504="Paid",M504="Cancelled",E504=""),"",IF(E504<TODAY(),"OVERDUE",IF(E504<=TODAY()+'Setup & Lists'!$M$7,"DUE SOON","")))

Sheet Cheque Register
A1: Cheque Register
A2: يرتبط كل شيك بالالتزام الأصلي؛ قيمة الشيك لا تُضاف مرة ثانية إلى الالتزامات
A4: Cheque No | B4: Commitment ID | C4: Branch | D4: Bank Account | E4: Beneficiary | F4: Issue Date | G4: Cheque Date | H4: Amount (AED) | I4: Status | J4: Cleared Date | K4: Replacement Cheque No | L4: Return Reason | M4: Days to Due | N4: Alert | O4: Notes
M5: =IFERROR(IF(G5="","",G5-TODAY()),"") | N5: =IFERROR(IF(OR(I5="Cleared",I5="Cancelled",G5=""),"",IF(G5<TODAY(),"OVERDUE",IF(G5<=TODAY()+'Setup & Lists'!$M$7,"DUE SOON",""))),"CHECK DATE")
M6: =IFERROR(IF(G6="","",G6-TODAY()),"") | N6: =IFERROR(IF(OR(I6="Cleared",I6="Cancelled",G6=""),"",IF(G6<TODAY(),"OVERDUE",IF(G6<=TODAY()+'Setup & Lists'!$M$7,"DUE SOON",""))),"CHECK DATE")
M7: =IFERROR(IF(G7="","",G7-TODAY()),"") | N7: =IFERROR(IF(OR(I7="Cleared",I7="Cancelled",G7=""),"",IF(G7<TODAY(),"OVERDUE",IF(G7<=TODAY()+'Setup & Lists'!$M$7,"DUE SOON",""))),"CHECK DATE")
M8: =IFERROR(IF(G8="","",G8-TODAY()),"") | N8: =IFERROR(IF(OR(I8="Cleared",I8="Cancelled",G8=""),"",IF(G8<TODAY(),"OVERDUE",IF(G8<=TODAY()+'Setup & Lists'!$M$7,"DUE SOON",""))),"CHECK DATE")
M9: =IFERROR(IF(G9="","",G9-TODAY()),"") | N9: =IFERROR(IF(OR(I9="Cleared",I9="Cancelled",G9=""),"",IF(G9<TODAY(),"OVERDUE",IF(G9<=TODAY()+'Setup & Lists'!$M$7,"DUE SOON",""))),"CHECK DATE")
M10: =IFERROR(IF(G10="","",G10-TODAY()),"") | N10: =IFERROR(IF(OR(I10="Cleared",I10="Cancelled",G10=""),"",IF(G10<TODAY(),"OVERDUE",IF(G10<=TODAY()+'Setup & Lists'!$M$7,"DUE SOON",""))),"CHECK DATE")
M11: =IFERROR(IF(G11="","",G11-TODAY()),"") | N11: =IFERROR(IF(OR(I11="Cleared",I11="Cancelled",G11=""),"",IF(G11<TODAY(),"OVERDUE",IF(G11<=TODAY()+'Setup & Lists'!$M$7,"DUE SOON",""))),"CHECK DATE")
M12: =IFERROR(IF(G12="","",G12-TODAY()),"") | N12: =IFERROR(IF(OR(I12="Cleared",I12="Cancelled",G12=""),"",IF(G12<TODAY(),"OVERDUE",IF(G12<=TODAY()+'Setup & Lists'!$M$7,"DUE SOON",""))),"CHECK DATE")
M13: =IFERROR(IF(G13="","",G13-TODAY()),"") | N13: =IFERROR(IF(OR(I13="Cleared",I13="Cancelled",G13=""),"",IF(G13<TODAY(),"OVERDUE",IF(G13<=TODAY()+'Setup & Lists'!$M$7,"DUE SOON",""))),"CHECK DATE")
M14: =IFERROR(IF(G14="","",G14-TODAY()),"") | N14: =IFERROR(IF(OR(I14="Cleared",I14="Cancelled",G14=""),"",IF(G14<TODAY(),"OVERDUE",IF(G14<=TODAY()+'Setup & Lists'!$M$7,"DUE SOON",""))),"CHECK DATE")
M15: =IFERROR(IF(G15="","",G15-TODAY()),"") | N15: =IFERROR(IF(OR(I15="Cleared",I15="Cancelled",G15=""),"",IF(G15<TODAY(),"OVERDUE",IF(G15<=TODAY()+'Setup & Lists'!$M$7,"DUE SOON",""))),"CHECK DATE")
M16: =IFERROR(IF(G16="","",G16-TODAY()),"") | N16: =IFERROR(IF(OR(I16="Cleared",I16="Cancelled",G16=""),"",IF(G16<TODAY(),"OVERDUE",IF(G16<=TODAY()+'Setup & Lists'!$M$7,"DUE SOON",""))),"CHECK DATE")
... M304: =IFERROR(IF(G304="","",G304-TODAY()),"") | N304: =IFERROR(IF(OR(I304="Cleared",I304="Cancelled",G304=""),"",IF(G304<TODAY(),"OVERDUE",IF(G304<=TODAY()+'Setup & Lists'!$M$7,"DUE SOON",""))),"CHECK DATE")

Sheet Accounts Payable
A1: Accounts Payable
A2: ذمم الموردين؛ كل فاتورة مفتوحة يجب أن ترتبط بـ Commitment ID واحد
A4: AP ID | B4: Commitment ID | C4: Supplier | D4: Invoice No | E4: Invoice Date | F4: Due Date | G4: Branch | H4: Category | I4: Amount (AED) | J4: Paid (AED) | K4: Balance (AED) | L4: Status | M4: Payment Method | N4: Purchase ID | O4: Duplicate Key | P4: Overdue Days | Q4: Alert | R4: Notes
K5: =IF(I5="","",MAX(0,I5-J5)) | O5: =IF(OR(C5="",D5=""),"",C5&"|"&D5&"|"&TEXT(I5,"0.00")) | P5: =IF(OR(F5="",K5=0),0,MAX(0,TODAY()-F5)) | Q5: =IF(OR(L5="Paid",L5="Cancelled",F5=""),"",IF(F5<TODAY(),"OVERDUE",IF(F5<=TODAY()+'Setup & Lists'!$M$7,"DUE SOON","")))
K6: =IF(I6="","",MAX(0,I6-J6)) | O6: =IF(OR(C6="",D6=""),"",C6&"|"&D6&"|"&TEXT(I6,"0.00")) | P6: =IF(OR(F6="",K6=0),0,MAX(0,TODAY()-F6)) | Q6: =IF(OR(L6="Paid",L6="Cancelled",F6=""),"",IF(F6<TODAY(),"OVERDUE",IF(F6<=TODAY()+'Setup & Lists'!$M$7,"DUE SOON","")))
K7: =IF(I7="","",MAX(0,I7-J7)) | O7: =IF(OR(C7="",D7=""),"",C7&"|"&D7&"|"&TEXT(I7,"0.00")) | P7: =IF(OR(F7="",K7=0),0,MAX(0,TODAY()-F7)) | Q7: =IF(OR(L7="Paid",L7="Cancelled",F7=""),"",IF(F7<TODAY(),"OVERDUE",IF(F7<=TODAY()+'Setup & Lists'!$M$7,"DUE SOON","")))
K8: =IF(I8="","",MAX(0,I8-J8)) | O8: =IF(OR(C8="",D8=""),"",C8&"|"&D8&"|"&TEXT(I8,"0.00")) | P8: =IF(OR(F8="",K8=0),0,MAX(0,TODAY()-F8)) | Q8: =IF(OR(L8="Paid",L8="Cancelled",F8=""),"",IF(F8<TODAY(),"OVERDUE",IF(F8<=TODAY()+'Setup & Lists'!$M$7,"DUE SOON","")))
K9: =IF(I9="","",MAX(0,I9-J9)) | O9: =IF(OR(C9="",D9=""),"",C9&"|"&D9&"|"&TEXT(I9,"0.00")) | P9: =IF(OR(F9="",K9=0),0,MAX(0,TODAY()-F9)) | Q9: =IF(OR(L9="Paid",L9="Cancelled",F9=""),"",IF(F9<TODAY(),"OVERDUE",IF(F9<=TODAY()+'Setup & Lists'!$M$7,"DUE SOON","")))
K10: =IF(I10="","",MAX(0,I10-J10)) | O10: =IF(OR(C10="",D10=""),"",C10&"|"&D10&"|"&TEXT(I10,"0.00")) | P10: =IF(OR(F10="",K10=0),0,MAX(0,TODAY()-F10)) | Q10: =IF(OR(L10="Paid",L10="Cancelled",F10=""),"",IF(F10<TODAY(),"OVERDUE",IF(F10<=TODAY()+'Setup & Lists'!$M$7,"DUE SOON","")))
K11: =IF(I11="","",MAX(0,I11-J11)) | O11: =IF(OR(C11="",D11=""),"",C11&"|"&D11&"|"&TEXT(I11,"0.00")) | P11: =IF(OR(F11="",K11=0),0,MAX(0,TODAY()-F11)) | Q11: =IF(OR(L11="Paid",L11="Cancelled",F11=""),"",IF(F11<TODAY(),"OVERDUE",IF(F11<=TODAY()+'Setup & Lists'!$M$7,"DUE SOON","")))
K12: =IF(I12="","",MAX(0,I12-J12)) | O12: =IF(OR(C12="",D12=""),"",C12&"|"&D12&"|"&TEXT(I12,"0.00")) | P12: =IF(OR(F12="",K12=0),0,MAX(0,TODAY()-F12)) | Q12: =IF(OR(L12="Paid",L12="Cancelled",F12=""),"",IF(F12<TODAY(),"OVERDUE",IF(F12<=TODAY()+'Setup & Lists'!$M$7,"DUE SOON","")))
K13: =IF(I13="","",MAX(0,I13-J13)) | O13: =IF(OR(C13="",D13=""),"",C13&"|"&D13&"|"&TEXT(I13,"0.00")) | P13: =IF(OR(F13="",K13=0),0,MAX(0,TODAY()-F13)) | Q13: =IF(OR(L13="Paid",L13="Cancelled",F13=""),"",IF(F13<TODAY(),"OVERDUE",IF(F13<=TODAY()+'Setup & Lists'!$M$7,"DUE SOON","")))
K14: =IF(I14="","",MAX(0,I14-J14)) | O14: =IF(OR(C14="",D14=""),"",C14&"|"&D14&"|"&TEXT(I14,"0.00")) | P14: =IF(OR(F14="",K14=0),0,MAX(0,TODAY()-F14)) | Q14: =IF(OR(L14="Paid",L14="Cancelled",F14=""),"",IF(F14<TODAY(),"OVERDUE",IF(F14<=TODAY()+'Setup & Lists'!$M$7,"DUE SOON","")))
K15: =IF(I15="","",MAX(0,I15-J15)) | O15: =IF(OR(C15="",D15=""),"",C15&"|"&D15&"|"&TEXT(I15,"0.00")) | P15: =IF(OR(F15="",K15=0),0,MAX(0,TODAY()-F15)) | Q15: =IF(OR(L15="Paid",L15="Cancelled",F15=""),"",IF(F15<TODAY(),"OVERDUE",IF(F15<=TODAY()+'Setup & Lists'!$M$7,"DUE SOON","")))
K16: =IF(I16="","",MAX(0,I16-J16)) | O16: =IF(OR(C16="",D16=""),"",C16&"|"&D16&"|"&TEXT(I16,"0.00")) | P16: =IF(OR(F16="",K16=0),0,MAX(0,TODAY()-F16)) | Q16: =IF(OR(L16="Paid",L16="Cancelled",F16=""),"",IF(F16<TODAY(),"OVERDUE",IF(F16<=TODAY()+'Setup & Lists'!$M$7,"DUE SOON","")))
... K504: =IF(I504="","",MAX(0,I504-J504)) | O504: =IF(OR(C504="",D504=""),"",C504&"|"&D504&"|"&TEXT(I504,"0.00")) | P504: =IF(OR(F504="",K504=0),0,MAX(0,TODAY()-F504)) | Q504: =IF(OR(L504="Paid",L504="Cancelled",F504=""),"",IF(F504<TODAY(),"OVERDUE",IF(F504<=TODAY()+'Setup & Lists'!$M$7,"DUE SOON","")))

Sheet Fixed Expenses
A1: Fixed Expenses Setup
A2: قوالب المصروفات الدورية؛ عند توليد الالتزام استخدم Source Type = Fixed وSource ID = Fixed ID
A4: Fixed ID | B4: Branch | C4: Expense Type | D4: Supplier / Payee | E4: Monthly Amount (AED) | F4: Due Day | G4: Start Date | H4: End Date | I4: Payment Method | J4: Active | K4: Source Reference | L4: Last Generated Month | M4: Next Due Date | N4: Notes
M5: =IF(OR(F5="",J5<>"Yes"),"",DATE(YEAR(TODAY()),MONTH(TODAY())+(DAY(TODAY())>F5),MIN(F5,DAY(EOMONTH(DATE(YEAR(TODAY()),MONTH(TODAY())+(DAY(TODAY())>F5),1),0)))))
M6: =IF(OR(F6="",J6<>"Yes"),"",DATE(YEAR(TODAY()),MONTH(TODAY())+(DAY(TODAY())>F6),MIN(F6,DAY(EOMONTH(DATE(YEAR(TODAY()),MONTH(TODAY())+(DAY(TODAY())>F6),1),0)))))
M7: =IF(OR(F7="",J7<>"Yes"),"",DATE(YEAR(TODAY()),MONTH(TODAY())+(DAY(TODAY())>F7),MIN(F7,DAY(EOMONTH(DATE(YEAR(TODAY()),MONTH(TODAY())+(DAY(TODAY())>F7),1),0)))))
M8: =IF(OR(F8="",J8<>"Yes"),"",DATE(YEAR(TODAY()),MONTH(TODAY())+(DAY(TODAY())>F8),MIN(F8,DAY(EOMONTH(DATE(YEAR(TODAY()),MONTH(TODAY())+(DAY(TODAY())>F8),1),0)))))
M9: =IF(OR(F9="",J9<>"Yes"),"",DATE(YEAR(TODAY()),MONTH(TODAY())+(DAY(TODAY())>F9),MIN(F9,DAY(EOMONTH(DATE(YEAR(TODAY()),MONTH(TODAY())+(DAY(TODAY())>F9),1),0)))))
M10: =IF(OR(F10="",J10<>"Yes"),"",DATE(YEAR(TODAY()),MONTH(TODAY())+(DAY(TODAY())>F10),MIN(F10,DAY(EOMONTH(DATE(YEAR(TODAY()),MONTH(TODAY())+(DAY(TODAY())>F10),1),0)))))
M11: =IF(OR(F11="",J11<>"Yes"),"",DATE(YEAR(TODAY()),MONTH(TODAY())+(DAY(TODAY())>F11),MIN(F11,DAY(EOMONTH(DATE(YEAR(TODAY()),MONTH(TODAY())+(DAY(TODAY())>F11),1),0)))))
M12: =IF(OR(F12="",J12<>"Yes"),"",DATE(YEAR(TODAY()),MONTH(TODAY())+(DAY(TODAY())>F12),MIN(F12,DAY(EOMONTH(DATE(YEAR(TODAY()),MONTH(TODAY())+(DAY(TODAY())>F12),1),0)))))
M13: =IF(OR(F13="",J13<>"Yes"),"",DATE(YEAR(TODAY()),MONTH(TODAY())+(DAY(TODAY())>F13),MIN(F13,DAY(EOMONTH(DATE(YEAR(TODAY()),MONTH(TODAY())+(DAY(TODAY())>F13),1),0)))))
M14: =IF(OR(F14="",J14<>"Yes"),"",DATE(YEAR(TODAY()),MONTH(TODAY())+(DAY(TODAY())>F14),MIN(F14,DAY(EOMONTH(DATE(YEAR(TODAY()),MONTH(TODAY())+(DAY(TODAY())>F14),1),0)))))
M15: =IF(OR(F15="",J15<>"Yes"),"",DATE(YEAR(TODAY()),MONTH(TODAY())+(DAY(TODAY())>F15),MIN(F15,DAY(EOMONTH(DATE(YEAR(TODAY()),MONTH(TODAY())+(DAY(TODAY())>F15),1),0)))))
M16: =IF(OR(F16="",J16<>"Yes"),"",DATE(YEAR(TODAY()),MONTH(TODAY())+(DAY(TODAY())>F16),MIN(F16,DAY(EOMONTH(DATE(YEAR(TODAY()),MONTH(TODAY())+(DAY(TODAY())>F16),1),0)))))
... M204: =IF(OR(F204="",J204<>"Yes"),"",DATE(YEAR(TODAY()),MONTH(TODAY())+(DAY(TODAY())>F204),MIN(F204,DAY(EOMONTH(DATE(YEAR(TODAY()),MONTH(TODAY())+(DAY(TODAY())>F204),1),0)))))

Sheet Cash Flow Forecast
A1: 12-Month Cash Flow Forecast
A2: دخل متوقع + التزامات فعلية + قوالب ثابتة، مع استبعاد Source Type = Fixed لمنع التكرار
A4: Month | B4: Opening Balance (AED) | C4: Expected Income (AED) | D4: Open Commitments (AED) | E4: Fixed Templates (AED) | F4: Expected Expenses (AED) | G4: Net Cash Flow (AED) | H4: Closing Balance (AED) | I4: Liquidity Alert | J4: Notes
A5: =DATE(YEAR(TODAY()),MONTH(TODAY())+0,1) | B5: =SUM('Bank & Cash Balances'!$I$5:$I$104) | D5: =SUMIFS(Commitments!$L$5:$L$504,Commitments!$E$5:$E$504,">="&A5,Commitments!$E$5:$E$504,"<="&EOMONTH(A5,0),Commitments!$M$5:$M$504,"<>Paid",Commitments!$M$5:$M$504,"<>Cancelled",Commitments!$B$5:$B$504,"<>Fixed") | E5: =SUMIFS('Fixed Expenses'!$E$5:$E$204,'Fixed Expenses'!$J$5:$J$204,"Yes",'Fixed Expenses'!$G$5:$G$204,"<="&EOMONTH(A5,0),'Fixed Expenses'!$H$5:$H$204,">="&A5)+SUMIFS('Fixed Expenses'!$E$5:$E$204,'Fixed Expenses'!$J$5:$J$204,"Yes",'Fixed Expenses'!$G$5:$G$204,"<="&EOMONTH(A5,0),'Fixed Expenses'!$H$5:$H$204,"") | F5: =D5+E5 | G5: =C5-F5 | H5: =B5+G5 | I5: =IF(H5<0,"CASH DEFICIT",IF(H5<'Setup & Lists'!$M$6,"LOW LIQUIDITY","OK"))
A6: =DATE(YEAR(TODAY()),MONTH(TODAY())+1,1) | B6: =H5 | D6: =SUMIFS(Commitments!$L$5:$L$504,Commitments!$E$5:$E$504,">="&A6,Commitments!$E$5:$E$504,"<="&EOMONTH(A6,0),Commitments!$M$5:$M$504,"<>Paid",Commitments!$M$5:$M$504,"<>Cancelled",Commitments!$B$5:$B$504,"<>Fixed") | E6: =SUMIFS('Fixed Expenses'!$E$5:$E$204,'Fixed Expenses'!$J$5:$J$204,"Yes",'Fixed Expenses'!$G$5:$G$204,"<="&EOMONTH(A6,0),'Fixed Expenses'!$H$5:$H$204,">="&A6)+SUMIFS('Fixed Expenses'!$E$5:$E$204,'Fixed Expenses'!$J$5:$J$204,"Yes",'Fixed Expenses'!$G$5:$G$204,"<="&EOMONTH(A6,0),'Fixed Expenses'!$H$5:$H$204,"") | F6: =D6+E6 | G6: =C6-F6 | H6: =B6+G6 | I6: =IF(H6<0,"CASH DEFICIT",IF(H6<'Setup & Lists'!$M$6,"LOW LIQUIDITY","OK"))
A7: =DATE(YEAR(TODAY()),MONTH(TODAY())+2,1) | B7: =H6 | D7: =SUMIFS(Commitments!$L$5:$L$504,Commitments!$E$5:$E$504,">="&A7,Commitments!$E$5:$E$504,"<="&EOMONTH(A7,0),Commitments!$M$5:$M$504,"<>Paid",Commitments!$M$5:$M$504,"<>Cancelled",Commitments!$B$5:$B$504,"<>Fixed") | E7: =SUMIFS('Fixed Expenses'!$E$5:$E$204,'Fixed Expenses'!$J$5:$J$204,"Yes",'Fixed Expenses'!$G$5:$G$204,"<="&EOMONTH(A7,0),'Fixed Expenses'!$H$5:$H$204,">="&A7)+SUMIFS('Fixed Expenses'!$E$5:$E$204,'Fixed Expenses'!$J$5:$J$204,"Yes",'Fixed Expenses'!$G$5:$G$204,"<="&EOMONTH(A7,0),'Fixed Expenses'!$H$5:$H$204,"") | F7: =D7+E7 | G7: =C7-F7 | H7: =B7+G7 | I7: =IF(H7<0,"CASH DEFICIT",IF(H7<'Setup & Lists'!$M$6,"LOW LIQUIDITY","OK"))
A8: =DATE(YEAR(TODAY()),MONTH(TODAY())+3,1) | B8: =H7 | D8: =SUMIFS(Commitments!$L$5:$L$504,Commitments!$E$5:$E$504,">="&A8,Commitments!$E$5:$E$504,"<="&EOMONTH(A8,0),Commitments!$M$5:$M$504,"<>Paid",Commitments!$M$5:$M$504,"<>Cancelled",Commitments!$B$5:$B$504,"<>Fixed") | E8: =SUMIFS('Fixed Expenses'!$E$5:$E$204,'Fixed Expenses'!$J$5:$J$204,"Yes",'Fixed Expenses'!$G$5:$G$204,"<="&EOMONTH(A8,0),'Fixed Expenses'!$H$5:$H$204,">="&A8)+SUMIFS('Fixed Expenses'!$E$5:$E$204,'Fixed Expenses'!$J$5:$J$204,"Yes",'Fixed Expenses'!$G$5:$G$204,"<="&EOMONTH(A8,0),'Fixed Expenses'!$H$5:$H$204,"") | F8: =D8+E8 | G8: =C8-F8 | H8: =B8+G8 | I8: =IF(H8<0,"CASH DEFICIT",IF(H8<'Setup & Lists'!$M$6,"LOW LIQUIDITY","OK"))
A9: =DATE(YEAR(TODAY()),MONTH(TODAY())+4,1) | B9: =H8 | D9: =SUMIFS(Commitments!$L$5:$L$504,Commitments!$E$5:$E$504,">="&A9,Commitments!$E$5:$E$504,"<="&EOMONTH(A9,0),Commitments!$M$5:$M$504,"<>Paid",Commitments!$M$5:$M$504,"<>Cancelled",Commitments!$B$5:$B$504,"<>Fixed") | E9: =SUMIFS('Fixed Expenses'!$E$5:$E$204,'Fixed Expenses'!$J$5:$J$204,"Yes",'Fixed Expenses'!$G$5:$G$204,"<="&EOMONTH(A9,0),'Fixed Expenses'!$H$5:$H$204,">="&A9)+SUMIFS('Fixed Expenses'!$E$5:$E$204,'Fixed Expenses'!$J$5:$J$204,"Yes",'Fixed Expenses'!$G$5:$G$204,"<="&EOMONTH(A9,0),'Fixed Expenses'!$H$5:$H$204,"") | F9: =D9+E9 | G9: =C9-F9 | H9: =B9+G9 | I9: =IF(H9<0,"CASH DEFICIT",IF(H9<'Setup & Lists'!$M$6,"LOW LIQUIDITY","OK"))
A10: =DATE(YEAR(TODAY()),MONTH(TODAY())+5,1) | B10: =H9 | D10: =SUMIFS(Commitments!$L$5:$L$504,Commitments!$E$5:$E$504,">="&A10,Commitments!$E$5:$E$504,"<="&EOMONTH(A10,0),Commitments!$M$5:$M$504,"<>Paid",Commitments!$M$5:$M$504,"<>Cancelled",Commitments!$B$5:$B$504,"<>Fixed") | E10: =SUMIFS('Fixed Expenses'!$E$5:$E$204,'Fixed Expenses'!$J$5:$J$204,"Yes",'Fixed Expenses'!$G$5:$G$204,"<="&EOMONTH(A10,0),'Fixed Expenses'!$H$5:$H$204,">="&A10)+SUMIFS('Fixed Expenses'!$E$5:$E$204,'Fixed Expenses'!$J$5:$J$204,"Yes",'Fixed Expenses'!$G$5:$G$204,"<="&EOMONTH(A10,0),'Fixed Expenses'!$H$5:$H$204,"") | F10: =D10+E10 | G10: =C10-F10 | H10: =B10+G10 | I10: =IF(H10<0,"CASH DEFICIT",IF(H10<'Setup & Lists'!$M$6,"LOW LIQUIDITY","OK"))
A11: =DATE(YEAR(TODAY()),MONTH(TODAY())+6,1) | B11: =H10 | D11: =SUMIFS(Commitments!$L$5:$L$504,Commitments!$E$5:$E$504,">="&A11,Commitments!$E$5:$E$504,"<="&EOMONTH(A11,0),Commitments!$M$5:$M$504,"<>Paid",Commitments!$M$5:$M$504,"<>Cancelled",Commitments!$B$5:$B$504,"<>Fixed") | E11: =SUMIFS('Fixed Expenses'!$E$5:$E$204,'Fixed Expenses'!$J$5:$J$204,"Yes",'Fixed Expenses'!$G$5:$G$204,"<="&EOMONTH(A11,0),'Fixed Expenses'!$H$5:$H$204,">="&A11)+SUMIFS('Fixed Expenses'!$E$5:$E$204,'Fixed Expenses'!$J$5:$J$204,"Yes",'Fixed Expenses'!$G$5:$G$204,"<="&EOMONTH(A11,0),'Fixed Expenses'!$H$5:$H$204,"") | F11: =D11+E11 | G11: =C11-F11 | H11: =B11+G11 | I11: =IF(H11<0,"CASH DEFICIT",IF(H11<'Setup & Lists'!$M$6,"LOW LIQUIDITY","OK"))
A12: =DATE(YEAR(TODAY()),MONTH(TODAY())+7,1) | B12: =H11 | D12: =SUMIFS(Commitments!$L$5:$L$504,Commitments!$E$5:$E$504,">="&A12,Commitments!$E$5:$E$504,"<="&EOMONTH(A12,0),Commitments!$M$5:$M$504,"<>Paid",Commitments!$M$5:$M$504,"<>Cancelled",Commitments!$B$5:$B$504,"<>Fixed") | E12: =SUMIFS('Fixed Expenses'!$E$5:$E$204,'Fixed Expenses'!$J$5:$J$204,"Yes",'Fixed Expenses'!$G$5:$G$204,"<="&EOMONTH(A12,0),'Fixed Expenses'!$H$5:$H$204,">="&A12)+SUMIFS('Fixed Expenses'!$E$5:$E$204,'Fixed Expenses'!$J$5:$J$204,"Yes",'Fixed Expenses'!$G$5:$G$204,"<="&EOMONTH(A12,0),'Fixed Expenses'!$H$5:$H$204,"") | F12: =D12+E12 | G12: =C12-F12 | H12: =B12+G12 | I12: =IF(H12<0,"CASH DEFICIT",IF(H12<'Setup & Lists'!$M$6,"LOW LIQUIDITY","OK"))
A13: =DATE(YEAR(TODAY()),MONTH(TODAY())+8,1) | B13: =H12 | D13: =SUMIFS(Commitments!$L$5:$L$504,Commitments!$E$5:$E$504,">="&A13,Commitments!$E$5:$E$504,"<="&EOMONTH(A13,0),Commitments!$M$5:$M$504,"<>Paid",Commitments!$M$5:$M$504,"<>Cancelled",Commitments!$B$5:$B$504,"<>Fixed") | E13: =SUMIFS('Fixed Expenses'!$E$5:$E$204,'Fixed Expenses'!$J$5:$J$204,"Yes",'Fixed Expenses'!$G$5:$G$204,"<="&EOMONTH(A13,0),'Fixed Expenses'!$H$5:$H$204,">="&A13)+SUMIFS('Fixed Expenses'!$E$5:$E$204,'Fixed Expenses'!$J$5:$J$204,"Yes",'Fixed Expenses'!$G$5:$G$204,"<="&EOMONTH(A13,0),'Fixed Expenses'!$H$5:$H$204,"") | F13: =D13+E13 | G13: =C13-F13 | H13: =B13+G13 | I13: =IF(H13<0,"CASH DEFICIT",IF(H13<'Setup & Lists'!$M$6,"LOW LIQUIDITY","OK"))
A14: =DATE(YEAR(TODAY()),MONTH(TODAY())+9,1) | B14: =H13 | D14: =SUMIFS(Commitments!$L$5:$L$504,Commitments!$E$5:$E$504,">="&A14,Commitments!$E$5:$E$504,"<="&EOMONTH(A14,0),Commitments!$M$5:$M$504,"<>Paid",Commitments!$M$5:$M$504,"<>Cancelled",Commitments!$B$5:$B$504,"<>Fixed") | E14: =SUMIFS('Fixed Expenses'!$E$5:$E$204,'Fixed Expenses'!$J$5:$J$204,"Yes",'Fixed Expenses'!$G$5:$G$204,"<="&EOMONTH(A14,0),'Fixed Expenses'!$H$5:$H$204,">="&A14)+SUMIFS('Fixed Expenses'!$E$5:$E$204,'Fixed Expenses'!$J$5:$J$204,"Yes",'Fixed Expenses'!$G$5:$G$204,"<="&EOMONTH(A14,0),'Fixed Expenses'!$H$5:$H$204,"") | F14: =D14+E14 | G14: =C14-F14 | H14: =B14+G14 | I14: =IF(H14<0,"CASH DEFICIT",IF(H14<'Setup & Lists'!$M$6,"LOW LIQUIDITY","OK"))
A15: =DATE(YEAR(TODAY()),MONTH(TODAY())+10,1) | B15: =H14 | D15: =SUMIFS(Commitments!$L$5:$L$504,Commitments!$E$5:$E$504,">="&A15,Commitments!$E$5:$E$504,"<="&EOMONTH(A15,0),Commitments!$M$5:$M$504,"<>Paid",Commitments!$M$5:$M$504,"<>Cancelled",Commitments!$B$5:$B$504,"<>Fixed") | E15: =SUMIFS('Fixed Expenses'!$E$5:$E$204,'Fixed Expenses'!$J$5:$J$204,"Yes",'Fixed Expenses'!$G$5:$G$204,"<="&EOMONTH(A15,0),'Fixed Expenses'!$H$5:$H$204,">="&A15)+SUMIFS('Fixed Expenses'!$E$5:$E$204,'Fixed Expenses'!$J$5:$J$204,"Yes",'Fixed Expenses'!$G$5:$G$204,"<="&EOMONTH(A15,0),'Fixed Expenses'!$H$5:$H$204,"") | F15: =D15+E15 | G15: =C15-F15 | H15: =B15+G15 | I15: =IF(H15<0,"CASH DEFICIT",IF(H15<'Setup & Lists'!$M$6,"LOW LIQUIDITY","OK"))
A16: =DATE(YEAR(TODAY()),MONTH(TODAY())+11,1) | B16: =H15 | D16: =SUMIFS(Commitments!$L$5:$L$504,Commitments!$E$5:$E$504,">="&A16,Commitments!$E$5:$E$504,"<="&EOMONTH(A16,0),Commitments!$M$5:$M$504,"<>Paid",Commitments!$M$5:$M$504,"<>Cancelled",Commitments!$B$5:$B$504,"<>Fixed") | E16: =SUMIFS('Fixed Expenses'!$E$5:$E$204,'Fixed Expenses'!$J$5:$J$204,"Yes",'Fixed Expenses'!$G$5:$G$204,"<="&EOMONTH(A16,0),'Fixed Expenses'!$H$5:$H$204,">="&A16)+SUMIFS('Fixed Expenses'!$E$5:$E$204,'Fixed Expenses'!$J$5:$J$204,"Yes",'Fixed Expenses'!$G$5:$G$204,"<="&EOMONTH(A16,0),'Fixed Expenses'!$H$5:$H$204,"") | F16: =D16+E16 | G16: =C16-F16 | H16: =B16+G16 | I16: =IF(H16<0,"CASH DEFICIT",IF(H16<'Setup & Lists'!$M$6,"LOW LIQUIDITY","OK"))

Sheet Bank & Cash Balances
A1: Bank & Cash Balances
A2: افصل الرصيد الدفتري عن الرصيد المتاح بعد الشيكات والحد الأدنى المحمي
A4: Account ID | B4: Branch | C4: Account Name | D4: Account Type | E4: As of Date | F4: Book Balance (AED) | G4: Pending Cheques (AED) | H4: Protected Minimum (AED) | I4: Available Balance (AED) | J4: Source | K4: Last Synced At | L4: Notes
A5: MBZ-BANK | B5: MBZ | C5: Main Bank — MBZ | D5: Bank | E5: 46193 | F5: 0 | G5: =IFERROR(IF(C5="","",SUMIFS('Cheque Register'!$H$5:$H$304,'Cheque Register'!$D$5:$D$304,C5,'Cheque Register'!$I$5:$I$304,"Pending")),0) | H5: ='Setup & Lists'!$M$6 | I5: =IFERROR(IF(F5="","",F5-G5-H5),0) | J5: Manual / POS
A6: MBZ-CASH | B6: MBZ | C6: Cash Box — MBZ | D6: Cash | E6: 46193 | F6: 0 | G6: =IFERROR(IF(C6="","",SUMIFS('Cheque Register'!$H$5:$H$304,'Cheque Register'!$D$5:$D$304,C6,'Cheque Register'!$I$5:$I$304,"Pending")),0) | H6: ='Setup & Lists'!$M$6 | I6: =IFERROR(IF(F6="","",F6-G6-H6),0) | J6: Manual / POS
A7: MUS-BANK | B7: Mussafah | C7: Main Bank — Mussafah | D7: Bank | E7: 46193 | F7: 0 | G7: =IFERROR(IF(C7="","",SUMIFS('Cheque Register'!$H$5:$H$304,'Cheque Register'!$D$5:$D$304,C7,'Cheque Register'!$I$5:$I$304,"Pending")),0) | H7: ='Setup & Lists'!$M$6 | I7: =IFERROR(IF(F7="","",F7-G7-H7),0) | J7: Manual / POS
A8: MUS-CASH | B8: Mussafah | C8: Cash Box — Mussafah | D8: Cash | E8: 46193 | F8: 0 | G8: =IFERROR(IF(C8="","",SUMIFS('Cheque Register'!$H$5:$H$304,'Cheque Register'!$D$5:$D$304,C8,'Cheque Register'!$I$5:$I$304,"Pending")),0) | H8: ='Setup & Lists'!$M$6 | I8: =IFERROR(IF(F8="","",F8-G8-H8),0) | J8: Manual / POS
A9: AF-BANK | B9: Al Falah | C9: ADIB BANK — Al Falah | D9: Bank | E9: 46193 | F9: 0 | G9: =IFERROR(IF(C9="","",SUMIFS('Cheque Register'!$H$5:$H$304,'Cheque Register'!$D$5:$D$304,C9,'Cheque Register'!$I$5:$I$304,"Pending")),0) | H9: ='Setup & Lists'!$M$6 | I9: =IFERROR(IF(F9="","",F9-G9-H9),0) | J9: Manual / POS
A10: AF-CASH | B10: Al Falah | C10: Cash Account — Al Falah | D10: Cash | E10: 46193 | F10: 0 | G10: =IFERROR(IF(C10="","",SUMIFS('Cheque Register'!$H$5:$H$304,'Cheque Register'!$D$5:$D$304,C10,'Cheque Register'!$I$5:$I$304,"Pending")),0) | H10: ='Setup & Lists'!$M$6 | I10: =IFERROR(IF(F10="","",F10-G10-H10),0) | J10: Manual / POS
G11: =IFERROR(IF(C11="","",SUMIFS('Cheque Register'!$H$5:$H$304,'Cheque Register'!$D$5:$D$304,C11,'Cheque Register'!$I$5:$I$304,"Pending")),0) | I11: =IFERROR(IF(F11="","",F11-G11-H11),0)
G12: =IFERROR(IF(C12="","",SUMIFS('Cheque Register'!$H$5:$H$304,'Cheque Register'!$D$5:$D$304,C12,'Cheque Register'!$I$5:$I$304,"Pending")),0) | I12: =IFERROR(IF(F12="","",F12-G12-H12),0)
G13: =IFERROR(IF(C13="","",SUMIFS('Cheque Register'!$H$5:$H$304,'Cheque Register'!$D$5:$D$304,C13,'Cheque Register'!$I$5:$I$304,"Pending")),0) | I13: =IFERROR(IF(F13="","",F13-G13-H13),0)
G14: =IFERROR(IF(C14="","",SUMIFS('Cheque Register'!$H$5:$H$304,'Cheque Register'!$D$5:$D$304,C14,'Cheque Register'!$I$5:$I$304,"Pending")),0) | I14: =IFERROR(IF(F14="","",F14-G14-H14),0)
G15: =IFERROR(IF(C15="","",SUMIFS('Cheque Register'!$H$5:$H$304,'Cheque Register'!$D$5:$D$304,C15,'Cheque Register'!$I$5:$I$304,"Pending")),0) | I15: =IFERROR(IF(F15="","",F15-G15-H15),0)
G16: =IFERROR(IF(C16="","",SUMIFS('Cheque Register'!$H$5:$H$304,'Cheque Register'!$D$5:$D$304,C16,'Cheque Register'!$I$5:$I$304,"Pending")),0) | I16: =IFERROR(IF(F16="","",F16-G16-H16),0)
G17: =IFERROR(IF(C17="","",SUMIFS('Cheque Register'!$H$5:$H$304,'Cheque Register'!$D$5:$D$304,C17,'Cheque Register'!$I$5:$I$304,"Pending")),0) | I17: =IFERROR(IF(F17="","",F17-G17-H17),0)
G18: =IFERROR(IF(C18="","",SUMIFS('Cheque Register'!$H$5:$H$304,'Cheque Register'!$D$5:$D$304,C18,'Cheque Register'!$I$5:$I$304,"Pending")),0) | I18: =IFERROR(IF(F18="","",F18-G18-H18),0)
G19: =IFERROR(IF(C19="","",SUMIFS('Cheque Register'!$H$5:$H$304,'Cheque Register'!$D$5:$D$304,C19,'Cheque Register'!$I$5:$I$304,"Pending")),0) | I19: =IFERROR(IF(F19="","",F19-G19-H19),0)
G20: =IFERROR(IF(C20="","",SUMIFS('Cheque Register'!$H$5:$H$304,'Cheque Register'!$D$5:$D$304,C20,'Cheque Register'!$I$5:$I$304,"Pending")),0) | I20: =IFERROR(IF(F20="","",F20-G20-H20),0)
G21: =IFERROR(IF(C21="","",SUMIFS('Cheque Register'!$H$5:$H$304,'Cheque Register'!$D$5:$D$304,C21,'Cheque Register'!$I$5:$I$304,"Pending")),0) | I21: =IFERROR(IF(F21="","",F21-G21-H21),0)
G22: =IFERROR(IF(C22="","",SUMIFS('Cheque Register'!$H$5:$H$304,'Cheque Register'!$D$5:$D$304,C22,'Cheque Register'!$I$5:$I$304,"Pending")),0) | I22: =IFERROR(IF(F22="","",F22-G22-H22),0)
... G104: =IFERROR(IF(C104="","",SUMIFS('Cheque Register'!$H$5:$H$304,'Cheque Register'!$D$5:$D$304,C104,'Cheque Register'!$I$5:$I$304,"Pending")),0) | I104: =IFERROR(IF(F104="","",F104-G104-H104),0)

Sheet Setup & Lists
A1: Setup & Lists
A2: قوائم التحكم المركزية — عدّل القيم هنا لتظهر في جميع الصفحات
A4: Branches | B4: Categories | C4: Payment Methods | D4: Commitment Status | E4: Cheque Status | F4: Priority | G4: Yes No | H4: Source Types | I4: Account Types | J4: AP Status | L4: Model Controls
A5: MBZ | B5: Rent | C5: Cash | D5: Draft | E5: Pending | F5: Critical | G5: Yes | H5: AP | I5: Bank | J5: Open | L5: Forecast Months | M5: 12
A6: Mussafah | B6: Salaries | C6: Credit Card | D6: Pending | E6: Cleared | F6: High | G6: No | H6: Cheque | I6: Cash | J6: Partially Paid | L6: Minimum Liquidity Buffer | M6: 10000
A7: Al Falah | B7: Laundry Supplies | C7: Bank Transfer | D7: Partially Paid | E7: Returned | F7: Normal | H7: Fixed | I7: Card Clearing | J7: Paid | L7: Alert Days | M7: 7
B8: Utilities | C8: Cheque | D8: Paid | E8: Cancelled | F8: Low | H8: Manual | J8: Disputed | L8: Currency | M8: AED
B9: Vehicle Expenses | C9: Credit | D9: On Hold | H9: POS | J9: Cancelled | L9: Last POS Sync | M9: Manual / n8n
B10: Maintenance | D10: Cancelled | H10: Payroll
B11: Government Fees
B12: Marketing
B13: Other
